djangocms_parallaxjs/__init__.py
djangocms_parallaxjs/admin.py
djangocms_parallaxjs/apps.py
djangocms_parallaxjs/cms_plugins.py
djangocms_parallaxjs/forms.py
djangocms_parallaxjs/models.py
djangocms_parallaxjs/tests.py
djangocms_parallaxjs/views.py
djangocms_parallaxjs/migrations/0001_initial.py
djangocms_parallaxjs/migrations/__init__.py
djangocms_parallaxjs/static/parallaxjs/js/parallax.min.js
djangocms_parallaxjs/templates/djangocms_parallaxjs/parallax.html
djangocms_parallaxjs-0.2.0.dist-info/LICENSE
djangocms_parallaxjs-0.2.0.dist-info/METADATA
djangocms_parallaxjs-0.2.0.dist-info/WHEEL
djangocms_parallaxjs-0.2.0.dist-info/top_level.txt
djangocms_parallaxjs-0.2.0.dist-info/RECORD
